django_ses_backend/__init__.py
django_ses_backend/backends.py
django_ses_backend-0.1.3.dist-info/LICENSE
django_ses_backend-0.1.3.dist-info/METADATA
django_ses_backend-0.1.3.dist-info/WHEEL
django_ses_backend-0.1.3.dist-info/RECORD
