Metadata-Version: 2.3
Name: django-ses-backend
Version: 0.1.3
Summary: Django email backend for AWS SES (Amazon Simple Email Service) without boto3
License: MIT
Keywords: django,email,aws,ses,backend
Author: Almaz Kunpeissov
Author-email: hello@akun.dev
Requires-Python: >=3.11
Classifier: Development Status :: 5 - Production/Stable
Classifier: Framework :: Django
Classifier: Framework :: Django :: 4.2
Classifier: Framework :: Django :: 5.0
Classifier: Framework :: Django :: 5.1
Classifier: Framework :: Django :: 5.2
Classifier: Intended Audience :: Developers
Classifier: License :: OSI Approved :: MIT License
Classifier: Operating System :: OS Independent
Classifier: Programming Language :: Python :: 3
Classifier: Programming Language :: Python :: 3.11
Classifier: Programming Language :: Python :: 3.12
Classifier: Programming Language :: Python :: 3.13
Classifier: Topic :: Communications :: Email
Requires-Dist: django (>=4.2,<6)
Project-URL: Bug Tracker, https://github.com/akun/django-ses-backend/issues
Project-URL: Changelog, https://github.com/almazkun/django-ses-backend/blob/main/CHANGELOG.md
Project-URL: Documentation, https://github.com/almazkun/django-ses-backend#readme
Project-URL: Homepage, https://github.com/almazkun/django-ses-backend
Project-URL: Repository, https://github.com/almazkun/django-ses-backend
